MANIFEST.in
setup.py
netbox_abrechnung/__init__.py
netbox_abrechnung/filtersets.py
netbox_abrechnung/forms.py
netbox_abrechnung/models.py
netbox_abrechnung/navigation.py
netbox_abrechnung/tables.py
netbox_abrechnung/template_content.py
netbox_abrechnung/urls.py
netbox_abrechnung/views.py
netbox_abrechnung.egg-info/PKG-INFO
netbox_abrechnung.egg-info/SOURCES.txt
netbox_abrechnung.egg-info/dependency_links.txt
netbox_abrechnung.egg-info/not-zip-safe
netbox_abrechnung.egg-info/top_level.txt
netbox_abrechnung/api/__init__.py
netbox_abrechnung/api/serializers.py
netbox_abrechnung/api/urls.py
netbox_abrechnung/api/views.py
netbox_abrechnung/migrations/0001_initial.py
netbox_abrechnung/migrations/0002_slavlan.py
netbox_abrechnung/migrations/__init__.py
netbox_abrechnung/templates/netbox_abrechnung/device.html
netbox_abrechnung/templates/netbox_abrechnung/kunde.html
netbox_abrechnung/templates/netbox_abrechnung/sla.html
netbox_abrechnung/templates/netbox_abrechnung/sladevice.html
netbox_abrechnung/templates/netbox_abrechnung/slavlan.html
netbox_abrechnung/templates/netbox_abrechnung/vlan.html