Metadata-Version: 2.1
Name: netbox-abrechnung
Version: 0.5
Summary: Manage Leistungsscheine in Netbox
Home-page: UNKNOWN
License: UNKNOWN
Platform: UNKNOWN
